[
  {
    "id": "1",
    "title": "کابینت آشپزخانه مدرن",
    "description": "طراحی و نصب کابینت‌های MDF با فینیش وود و هاردور آلمانی",
    "image": "/kitchen-cabinet-1.jpg",
    "category": "آشپزخانه"
  },
  {
    "id": "2",
    "title": "کابینت آشپزخانه با فضای ذخیره",
    "description": "کابینت‌های MDF با سبد کشویی و سازمان‌دهندگی داخلی",
    "image": "/kitchen-cabinet-2.jpg",
    "category": "آشپزخانه"
  },
  {
    "id": "3",
    "title": "تخت خواب با میز ارایشی",
    "description": "طراحی یکپارچه تخت خواب با فضای ذخیره و میز ارایشی چوبی",
    "image": "/bedroom-cabinet-1.jpg",
    "category": "اتاق خواب"
  },
  {
    "id": "4",
    "title": "میز ارایشی و کمد اتاق خواب",
    "description": "میز ارایشی با درایور و کمد دیواری برای ذخیره‌سازی",
    "image": "/bedroom-cabinet-2.jpg",
    "category": "اتاق خواب"
  },
  {
    "id": "5",
    "title": "پنل‌های دیواری MDF",
    "description": "پنل‌های دیواری MDF با طراحی مدرن و فینیش‌های متنوع",
    "image": "/mdf-panel-1.jpg",
    "category": "پنل و آسانسور"
  },
  {
    "id": "6",
    "title": "آسانسور خانگی",
    "description": "نصب و طراحی آسانسور خانگی با درب‌های MDF و دکوراتیو",
    "image": "/elevator-1.jpg",
    "category": "پنل و آسانسور"
  },
  {
    "id": "7",
    "title": "قفسه‌های شناور",
    "description": "قفسه‌های چوبی شناور با طراحی معاصر برای نمایش اشیاء",
    "image": "/shelves-1.jpg",
    "category": "دکوراتیو"
  },
  {
    "id": "8",
    "title": "دیوار‌کوب تلویزیون",
    "description": "کابینت‌های تلویزیون با فضای ذخیره‌سازی یکپارچه و نورپردازی",
    "image": "/tv-wall-1.jpg",
    "category": "دکوراتیو"
  }
]